arruda/transformations.py
arruda-0.1.0.dist-info/METADATA
arruda-0.1.0.dist-info/WHEEL
arruda-0.1.0.dist-info/RECORD
