Metadata-Version: 2.1
Name: arruda
Version: 0.1.0
Summary: Feature transformation for health related data 🍃
Author: Ana Paula Gomes
Author-email: apgomes88@gmail.com
Requires-Python: >=3.10,<4.0
Classifier: Programming Language :: Python :: 3
Classifier: Programming Language :: Python :: 3.10
Classifier: Programming Language :: Python :: 3.11
Requires-Dist: pandas (>=2.2.0,<3.0.0)
